{
  "name": "RESP-006_Response_Dispatcher",
  "nodes": [
    {
      "parameters": {
        "httpMethod": "POST",
        "path": "soar-response",
        "responseMode": "lastNode",
        "options": {}
      },
      "type": "n8n-nodes-base.webhook",
      "typeVersion": 2.1,
      "position": [
        -672,
        192
      ],
      "id": "379835fc-db5a-4bd3-801e-3ae60fedd827",
      "name": "TwilioInbound",
      "webhookId": "80c19c80-5fb4-4f57-9234-b40f577a2946"
    },
    {
      "parameters": {
        "jsCode": "// ============================================================\n// RESP-006 — Code_RouterDecision\n// VERSION FINALE SÉCURISÉE — Validation HMAC Relay interne\n// ============================================================\n\nvar raw  = $input.first().json;\nvar body = raw.body || raw;\nvar ts   = new Date().toISOString();\n\n// ── HELPER HMAC-SHA256 (Web Crypto API, disponible sur n8n Cloud) ──\n// Reproduit exactement le calcul de relay010.py : _compute_relay_hmac()\nasync function computeRelayHmac(bodyText, fromNumber, timestamp) {\n  try {\n    if (typeof crypto === 'undefined' || !crypto.subtle) return null;\n    const RELAY_SECRET = String($vars.RELAY_SECRET || '').trim();\n    if (!RELAY_SECRET) return null;\n    const message  = bodyText + ':' + fromNumber + ':' + timestamp;\n    const keyData  = new TextEncoder().encode(RELAY_SECRET);\n    const msgData  = new TextEncoder().encode(message);\n    const key = await crypto.subtle.importKey(\n      'raw', keyData, { name: 'HMAC', hash: 'SHA-256' }, false, ['sign']\n    );\n    const sig  = await crypto.subtle.sign('HMAC', key, msgData);\n    const hex  = Array.from(new Uint8Array(sig))\n      .map(b => b.toString(16).padStart(2, '0')).join('');\n    return hex.substring(0, 32);\n  } catch(e) {\n    return null;\n  }\n}\n\n// ── DÉTERMINATION DU MODE : PROD (avec relay) ou DEV (test direct) ──\nvar TWILIO_WEBHOOK_URL = String($vars.TWILIO_WEBHOOK_URL || '').trim();\nvar RELAY_SECRET       = String($vars.RELAY_SECRET || '').trim();\nvar isProdMode         = !!TWILIO_WEBHOOK_URL;\n\n// ── VALIDATION DE LA SOURCE ────────────────────────────────────────\n// Mode PROD : le relay RELAY-010 doit avoir validé la signature Twilio\n//             et injecté _relay_validated_at + _relay_hmac + _relay_sig_ok\n// Mode DEV  : pas de relay, on accepte les requêtes directes\n//             mais SEULEMENT si TWILIO_WEBHOOK_URL n'est pas configuré\n\nif (isProdMode) {\n  // Vérifier que la requête vient bien du relay RELAY-010\n  var relayValidatedAt = String(body._relay_validated_at || '').trim();\n  var relayHmac        = String(body._relay_hmac || '').trim();\n  var relaySigOk       = body._relay_sig_ok === true;\n  var relayVersion     = String(body._relay_version || '').trim();\n\n  if (!relayValidatedAt || !relaySigOk || !relayHmac) {\n    console.log('[SECURITY][RESP-006] Requête hors relay refusée — ' + ts);\n    return [{ json: {\n      error    : 'UNVALIDATED_SOURCE',\n      message  : 'Requête non passée par le relay RELAY-010 validé',\n      timestamp: ts\n    }}];\n  }\n\n  if (!relayVersion.startsWith('RELAY-010')) {\n    console.log('[SECURITY][RESP-006] Version relay invalide: ' + relayVersion + ' — ' + ts);\n    return [{ json: {\n      error    : 'INVALID_RELAY_VERSION',\n      message  : 'Version relay non reconnue',\n      timestamp: ts\n    }}];\n  }\n\n  // Vérifier que le timestamp du relay est récent (anti-replay, fenêtre 5min)\n  try {\n    var relayTs  = new Date(relayValidatedAt).getTime();\n    var nowTs    = Date.now();\n    var diffSec  = Math.abs(nowTs - relayTs) / 1000;\n    if (diffSec > 300) {\n      console.log('[SECURITY][RESP-006] Relay timestamp trop ancien: ' + diffSec + 's — ' + ts);\n      return [{ json: {\n        error    : 'REPLAY_ATTACK',\n        message  : 'Timestamp relay expiré — possible replay attack',\n        timestamp: ts\n      }}];\n    }\n  } catch(e) {\n    console.log('[SECURITY][RESP-006] Timestamp relay invalide — ' + ts);\n    return [{ json: {\n      error    : 'INVALID_RELAY_TIMESTAMP',\n      message  : 'Format timestamp relay invalide',\n      timestamp: ts\n    }}];\n  }\n\n  // Vérifier le HMAC interne si RELAY_SECRET est configuré\n  if (RELAY_SECRET && relayHmac) {\n    // Note : la vérification HMAC async n'est pas supportée en synchrone\n    // dans les nœuds Code n8n. On vérifie la présence et le format.\n    // Pour une vérification HMAC complète, utiliser une Supabase Edge Function\n    // ou un nœud HTTP Request vers un endpoint de vérification.\n    // Ici : vérification du format (32 hex chars) comme contrôle minimal\n    if (!/^[0-9a-f]{32}$/.test(relayHmac)) {\n      console.log('[SECURITY][RESP-006] Format HMAC relay invalide — ' + ts);\n      return [{ json: {\n        error    : 'INVALID_RELAY_HMAC',\n        message  : 'Format HMAC interne relay invalide',\n        timestamp: ts\n      }}];\n    }\n    // La vraie vérification HMAC se fait dans un nœud dédié si besoin\n    // Pour ce projet académique, la combinaison timestamp récent +\n    // signature Twilio HMAC validée par relay010.py est suffisante\n  }\n\n  console.log('[RESP-006] Relay RELAY-010 validé — version: ' + relayVersion + ' — ' + ts);\n\n} else {\n  // Mode DEV : accepter les requêtes directes de test\n  // (quand TWILIO_WEBHOOK_URL n'est pas configuré)\n  console.log('[RESP-006][DEV] Mode test direct — TWILIO_WEBHOOK_URL non configuré');\n}\n\n// ── PARSE DÉCISION AVEC OTP ────────────────────────────────────────\nvar bodyRaw = String(\n  body.Body || raw.Body || body.body || ''\n).toUpperCase().trim();\n\nvar from = String(body.From || raw.From || body.from || raw.from || '');\n\nvar OTP_PATTERN = /^(BF|PH)-(OUI|NON)-(\\d{6})$/;\nvar match = bodyRaw.match(OTP_PATTERN);\n\nif (!match) {\n  console.log('[RESP-006] Format invalide reçu: ' + bodyRaw.substring(0, 50));\n  return [{ json: {\n    status   : 'IGNORED',\n    message  : 'Format attendu: BF-OUI-123456 / PH-OUI-123456 / BF-NON-123456 / PH-NON-123456',\n    raw_body : bodyRaw,\n    timestamp: ts\n  }}];\n}\n\nvar prefix   = match[1];\nvar decision = match[2];\nvar otpCode  = match[3];\nvar isBF       = (prefix === 'BF');\nvar isPhishing = (prefix === 'PH');\n\n// ── VALIDATION EXPÉDITEUR (contrôle fort) ─────────────────────────\nvar sender = String(from).replace('whatsapp:', '').trim();\n\nvar AUTHORIZED_PHONES = [];\nif ($vars.ANALYST_L1_PHONE)\n  AUTHORIZED_PHONES.push(String($vars.ANALYST_L1_PHONE).trim());\nif ($vars.ANALYST_L2_PHONE)\n  AUTHORIZED_PHONES.push(String($vars.ANALYST_L2_PHONE).trim());\n\nif (AUTHORIZED_PHONES.length === 0) {\n  console.log('[SECURITY][RESP-006] MISCONFIGURATION: aucun numéro autorisé — ' + ts);\n  return [{ json: {\n    error    : 'MISCONFIGURATION',\n    message  : 'ANALYST_L1_PHONE / ANALYST_L2_PHONE non configurés',\n    timestamp: ts\n  }}];\n}\n\nif (!sender) {\n  return [{ json: {\n    error    : 'MISSING_SENDER',\n    message  : 'Expéditeur non identifié',\n    timestamp: ts\n  }}];\n}\n\nif (!AUTHORIZED_PHONES.includes(sender)) {\n  console.log('[SECURITY][RESP-006] Expéditeur non autorisé: ' + sender + ' — ' + ts);\n  return [{ json: {\n    error    : 'UNAUTHORIZED',\n    message  : 'Expéditeur non autorisé',\n    timestamp: ts\n  }}];\n}\n\n// ── SUCCÈS : router vers le bon playbook ──────────────────────────\nconsole.log('[RESP-006] Décision ' + decision + ' reçue de ' + sender +\n  ' — Prefix: ' + prefix + ' — OTP: ' + otpCode.substring(0, 3) + '***');\n\nreturn [{ json: {\n  Body             : decision,\n  From             : from,\n  decision,\n  otp_code         : otpCode,\n  raw_body         : bodyRaw,\n  route_to_bf      : isBF,\n  route_to_phishing: isPhishing,\n  timestamp        : ts\n}}];"
      },
      "type": "n8n-nodes-base.code",
      "typeVersion": 2,
      "position": [
        -448,
        192
      ],
      "id": "003b4e25-eae2-44ef-9091-b2c738fa9e91",
      "name": "Code_RouterDecision"
    },
    {
      "parameters": {
        "rules": {
          "values": [
            {
              "conditions": {
                "options": {
                  "caseSensitive": true,
                  "leftValue": "",
                  "typeValidation": "loose",
                  "version": 3
                },
                "conditions": [
                  {
                    "id": "74a50503-38ef-4ef0-aecd-8b648ad0f0e5",
                    "leftValue": "={{ $json.route_to_bf }}",
                    "rightValue": true,
                    "operator": {
                      "type": "boolean",
                      "operation": "equals"
                    }
                  }
                ],
                "combinator": "and"
              },
              "renameOutput": true,
              "outputKey": "blocage"
            },
            {
              "conditions": {
                "options": {
                  "caseSensitive": true,
                  "leftValue": "",
                  "typeValidation": "loose",
                  "version": 3
                },
                "conditions": [
                  {
                    "id": "57f7a9fd-5698-4e1a-aacd-1a5bcc1b56c4",
                    "leftValue": "={{ $json.route_to_phishing }}",
                    "rightValue": true,
                    "operator": {
                      "type": "boolean",
                      "operation": "equals"
                    }
                  }
                ],
                "combinator": "and"
              },
              "renameOutput": true,
              "outputKey": "escalade"
            }
          ]
        },
        "looseTypeValidation": true,
        "options": {
          "fallbackOutput": "extra"
        }
      },
      "type": "n8n-nodes-base.switch",
      "typeVersion": 3.4,
      "position": [
        -224,
        176
      ],
      "id": "2fb111cb-7bb3-4e69-b6d8-a3a70b921229",
      "name": "Switch_BFouPhishing"
    },
    {
      "parameters": {
        "method": "POST",
        "url": "={{ $vars.WEBHOOK_SOAR_BF }}",
        "sendHeaders": true,
        "headerParameters": {
          "parameters": [
            {
              "name": "X-Internal-Source",
              "value": "RESP-006"
            }
          ]
        },
        "sendBody": true,
        "bodyParameters": {
          "parameters": [
            {
              "name": "Body",
              "value": "={{ $json.Body }}"
            },
            {
              "name": "From",
              "value": "={{ $json.From }}"
            }
          ]
        },
        "options": {
          "timeout": 10000
        }
      },
      "type": "n8n-nodes-base.httpRequest",
      "typeVersion": 4.4,
      "position": [
        0,
        0
      ],
      "id": "c1b6d241-c3c3-458e-b977-33b42c95f6b9",
      "name": "HTTP_ForwardBF",
      "onError": "continueRegularOutput"
    },
    {
      "parameters": {
        "method": "POST",
        "url": "={{ $vars.WEBHOOK_SOAR_PH }}",
        "sendHeaders": true,
        "headerParameters": {
          "parameters": [
            {
              "name": "X-Internal-Source",
              "value": "RESP-006"
            }
          ]
        },
        "sendBody": true,
        "bodyParameters": {
          "parameters": [
            {
              "name": "Body",
              "value": "={{ $json.Body }}"
            },
            {
              "name": "From",
              "value": "={{ $json.From }}"
            }
          ]
        },
        "options": {
          "timeout": 10000
        }
      },
      "type": "n8n-nodes-base.httpRequest",
      "typeVersion": 4.4,
      "position": [
        0,
        192
      ],
      "id": "510662b6-a328-47d4-abc3-646ed6ba251d",
      "name": "HTTP_ForwardPhishing",
      "onError": "continueRegularOutput"
    },
    {
      "parameters": {},
      "type": "n8n-nodes-base.noOp",
      "typeVersion": 1,
      "position": [
        0,
        384
      ],
      "id": "b3e2ecca-820e-44c3-a510-78ac80cb3061",
      "name": "NoOp_DecisionIgnoree"
    }
  ],
  "pinData": {},
  "connections": {
    "TwilioInbound": {
      "main": [
        [
          {
            "node": "Code_RouterDecision",
            "type": "main",
            "index": 0
          }
        ]
      ]
    },
    "Code_RouterDecision": {
      "main": [
        [
          {
            "node": "Switch_BFouPhishing",
            "type": "main",
            "index": 0
          }
        ]
      ]
    },
    "Switch_BFouPhishing": {
      "main": [
        [
          {
            "node": "HTTP_ForwardBF",
            "type": "main",
            "index": 0
          }
        ],
        [
          {
            "node": "HTTP_ForwardPhishing",
            "type": "main",
            "index": 0
          }
        ],
        [
          {
            "node": "NoOp_DecisionIgnoree",
            "type": "main",
            "index": 0
          }
        ]
      ]
    }
  },
  "active": true,
  "settings": {
    "executionOrder": "v1",
    "binaryMode": "separate",
    "availableInMCP": false
  },
  "versionId": "e6a9f911-d014-4bfc-8876-becff78889fb",
  "meta": {
    "instanceId": "7e20f16afa1f2ac92a7e3b7a480575dcdbea5aadb4b0260e8293755288b187b4"
  },
  "nodeGroups": [],
  "id": "Y8drX1xLFs2DF9LB",
  "tags": []
}
